{
  "configVersion": 1,
  "index": "/index.html",
  "assetGroups": [
    {
      "name": "app",
      "installMode": "prefetch",
      "updateMode": "prefetch",
      "urls": [
        "/es2015-polyfills.358ed1827c991dd2afb0.js",
        "/favicon.ico",
        "/index.html",
        "/main.57d8e6774d70c0bb811e.js",
        "/polyfills.407a467dedb63cfdd103.js",
        "/runtime.a5dd35324ddfd942bef1.js",
        "/styles.d9c7ef31625b4f970066.css"
      ],
      "patterns": []
    },
    {
      "name": "assets",
      "installMode": "lazy",
      "updateMode": "prefetch",
      "urls": [
        "/assets/icons/icon-128x128.png",
        "/assets/icons/icon-144x144.png",
        "/assets/icons/icon-152x152.png",
        "/assets/icons/icon-192x192.png",
        "/assets/icons/icon-384x384.png",
        "/assets/icons/icon-512x512.png",
        "/assets/icons/icon-72x72.png",
        "/assets/icons/icon-96x96.png"
      ],
      "patterns": []
    },
    {
      "name": "fonts",
      "installMode": "prefetch",
      "updateMode": "prefetch",
      "urls": [],
      "patterns": [
        "https:\\/\\/fonts\\.googleapis\\.com\\/.*",
        "https:\\/\\/fonts\\.gstatic\\.com\\/.*"
      ]
    },
    {
      "name": "api",
      "installMode": "prefetch",
      "updateMode": "prefetch",
      "urls": [],
      "patterns": [
        "http:\\/\\/localhost:3000\\/.*"
      ]
    }
  ],
  "dataGroups": [],
  "hashTable": {
    "/assets/icons/icon-128x128.png": "dae3b6ed49bdaf4327b92531d4b5b4a5d30c7532",
    "/assets/icons/icon-144x144.png": "b0bd89982e08f9bd2b642928f5391915b74799a7",
    "/assets/icons/icon-152x152.png": "7479a9477815dfd9668d60f8b3b2fba709b91310",
    "/assets/icons/icon-192x192.png": "1abd80d431a237a853ce38147d8c63752f10933b",
    "/assets/icons/icon-384x384.png": "329749cd6393768d3131ed6304c136b1ca05f2fd",
    "/assets/icons/icon-512x512.png": "559d9c4318b45a1f2b10596bbb4c960fe521dbcc",
    "/assets/icons/icon-72x72.png": "c457e56089a36952cd67156f9996bc4ce54a5ed9",
    "/assets/icons/icon-96x96.png": "3914125a4b445bf111c5627875fc190f560daa41",
    "/es2015-polyfills.358ed1827c991dd2afb0.js": "b7a81c61d32b0b12737f0c13f45973ba391cd7f9",
    "/favicon.ico": "84161b857f5c547e3699ddfbffc6d8d737542e01",
    "/index.html": "a510719374a1c1135a1082b2d3053fed2fcbed7a",
    "/main.57d8e6774d70c0bb811e.js": "b185cb874e1e46de63c2c9fd801b0ac0dc92101d",
    "/polyfills.407a467dedb63cfdd103.js": "ffa449995bf2eba2ccd0a002417214f7eb75e7b5",
    "/runtime.a5dd35324ddfd942bef1.js": "b62956c2192bfe5516d6374e753773901ed50ec5",
    "/styles.d9c7ef31625b4f970066.css": "32cd7d8871edb03bb95703e75bc75302f263dc78"
  },
  "navigationUrls": [
    {
      "positive": true,
      "regex": "^\\/.*$"
    },
    {
      "positive": false,
      "regex": "^\\/(?:.+\\/)?[^/]*\\.[^/]*$"
    },
    {
      "positive": false,
      "regex": "^\\/(?:.+\\/)?[^/]*__[^/]*$"
    },
    {
      "positive": false,
      "regex": "^\\/(?:.+\\/)?[^/]*__[^/]*\\/.*$"
    }
  ]
}